openrocketengine/__init__.py
openrocketengine/core/__init__.py
openrocketengine/core/interface.py
openrocketengine/core/rocket.py
openrocketengine/core/writer.py
openrocketengine/tests/__init__.py
openrocketengine/tests/test_rocket.py
openrocketengine-0.0.4.dist-info/METADATA
openrocketengine-0.0.4.dist-info/RECORD
openrocketengine-0.0.4.dist-info/WHEEL
openrocketengine-0.0.4.dist-info/entry_points.txt
openrocketengine-0.0.4.dist-info/top_level.txt
