Metadata-Version: 2.1
Name: openrocketengine
Version: 0.0.4
Summary: An opensource rocket engine designer
Home-page: https://github.com/cmflannery/openrocketengine
Author: cameron
Author-email: 
License: UNKNOWN
Keywords: rocket engines
Platform: UNKNOWN
Classifier: Development Status :: 3 - Alpha
Classifier: Intended Audience :: Developers
Classifier: Topic :: Software Development :: Build Tools
Classifier: License :: OSI Approved :: MIT License
Classifier: Programming Language :: Python :: 3
Classifier: Programming Language :: Python :: 3.5
Classifier: Programming Language :: Python :: 3.6
Classifier: Programming Language :: Python :: 3.7
Provides-Extra: test
Provides-Extra: dev
Requires-Dist: numpy (>=1.0)
Requires-Dist: pandas (>=0.20)
Requires-Dist: fire (>=0.1.3)
Requires-Dist: pytest
Requires-Dist: xlsxwriter
Provides-Extra: dev
Requires-Dist: check-manifest; extra == 'dev'
Provides-Extra: test
Requires-Dist: coverage; extra == 'test'
